topsis/__init__.py
topsis/topsis.py
topsis_sneha_102303723-1.0.0.dist-info/METADATA
topsis_sneha_102303723-1.0.0.dist-info/WHEEL
topsis_sneha_102303723-1.0.0.dist-info/entry_points.txt
topsis_sneha_102303723-1.0.0.dist-info/top_level.txt
topsis_sneha_102303723-1.0.0.dist-info/RECORD
