Metadata-Version: 2.2
Name: topsis-sneha-102303723
Version: 1.0.0
Summary: TOPSIS implementation using Python
Author: Sneha
Author-email: ssneha1_be23@thapar.edu
Requires-Dist: pandas
Requires-Dist: numpy
Dynamic: author
Dynamic: author-email
Dynamic: description
Dynamic: description-content-type
Dynamic: requires-dist
Dynamic: summary
